Metadata-Version: 2.1
Name: fast-ensemble
Version: 0.0.1
Summary: Library for high level model ensembling
Home-page: https://github.com/leffff/fast-ensemble
Author: leffff
Author-email: levnovitskiy@gmail.com
License: MIT
Platform: UNKNOWN
Classifier: Programming Language :: Python :: 3
Classifier: Operating System :: OS Independent
Requires-Python: >=3.8
License-File: LICENSE
